katalytic_images-0.14.0.dist-info/METADATA
katalytic_images-0.14.0.dist-info/WHEEL
katalytic_images-0.14.0.dist-info/entry_points.txt
katalytic_images-0.14.0.dist-info/licenses/LICENSE.txt
katalytic_images/__init__.py
katalytic_images/images.py
katalytic_images-0.14.0.dist-info/RECORD
