Metadata-Version: 2.1
Name: katalytic-images
Version: 0.14.0
Summary: This plugin adds utilities for working with images and videos to the katalytic namespace
Author-Email: Valentin Neagu <vali19th@protonmail.com>
License: Copyright 2023 - present, Valentin Neagu
Classifier: Development Status :: 3 - Alpha
Classifier: Intended Audience :: Developers
Classifier: Intended Audience :: Science/Research
Classifier: License :: OSI Approved :: MIT License
Classifier: Natural Language :: English
Classifier: Operating System :: OS Independent
Classifier: Programming Language :: Python :: 3
Classifier: Topic :: Scientific/Engineering :: Artificial Intelligence
Classifier: Topic :: Scientific/Engineering :: Image Processing
Classifier: Topic :: Scientific/Engineering :: Visualization
Classifier: Topic :: Scientific/Engineering
Classifier: Topic :: Software Development :: Libraries
Classifier: Topic :: Utilities
Project-URL: Changelog, https://gitlab.com/katalytic/katalytic-images/-/blob/main/CHANGELOG.md
Project-URL: Homepage, https://gitlab.com/katalytic/katalytic-images.git
Project-URL: Repository, https://gitlab.com/katalytic/katalytic-images.git
Requires-Python: >=3.13
Requires-Dist: katalytic>=0.4.1
Requires-Dist: numpy>=1.14
Requires-Dist: pillow>=8.4.0
Provides-Extra: dev
Requires-Dist: black; extra == "dev"
Requires-Dist: pre-commit; extra == "dev"
Requires-Dist: pytest; extra == "dev"
Requires-Dist: pytest-cov; extra == "dev"
Requires-Dist: pytest-clarity; extra == "dev"
Requires-Dist: pytest-randomly; extra == "dev"
